README.rst
setup.py
package_boilerplate/__init__.py
package_boilerplate/main.py
package_boilerplate.egg-info/PKG-INFO
package_boilerplate.egg-info/SOURCES.txt
package_boilerplate.egg-info/dependency_links.txt
package_boilerplate.egg-info/not-zip-safe
package_boilerplate.egg-info/top_level.txt
test/test.py